{
  "annotations": {
    "list": [
      {
        "builtIn": 1,
        "datasource": { "type": "grafana", "uid": "-- Grafana --" },
        "enable": true,
        "hide": true,
        "iconColor": "rgba(0, 211, 255, 1)",
        "name": "Annotations & Alerts",
        "type": "dashboard"
      }
    ]
  },
  "description": "Lastmile Gig Platform Overview - Live orders, drivers, revenue, error rate",
  "editable": true,
  "fiscalYearStartMonth": 0,
  "graphTooltip": 1,
  "id": null,
  "links": [],
  "liveNow": true,
  "panels": [
    {
      "datasource": { "type": "prometheus", "uid": "prometheus" },
      "fieldConfig": {
        "defaults": {
          "color": { "mode": "thresholds" },
          "thresholds": {
            "mode": "absolute",
            "steps": [
              { "color": "green", "value": null },
              { "color": "yellow", "value": 100 },
              { "color": "red", "value": 500 }
            ]
          },
          "unit": "none"
        }
      },
      "gridPos": { "h": 4, "w": 6, "x": 0, "y": 0 },
      "id": 1,
      "options": {
        "colorMode": "background",
        "graphMode": "area",
        "justifyMode": "auto",
        "orientation": "auto",
        "reduceOptions": { "calcs": ["lastNotNull"], "fields": "", "values": false },
        "textMode": "auto"
      },
      "title": "Active Orders",
      "type": "stat",
      "targets": [
        {
          "expr": "sum(lmg_orders_active_total)",
          "legendFormat": "Active Orders",
          "refId": "A"
        }
      ]
    },
    {
      "datasource": { "type": "prometheus", "uid": "prometheus" },
      "fieldConfig": {
        "defaults": {
          "color": { "mode": "thresholds" },
          "thresholds": {
            "mode": "absolute",
            "steps": [
              { "color": "red", "value": null },
              { "color": "yellow", "value": 50 },
              { "color": "green", "value": 100 }
            ]
          },
          "unit": "none"
        }
      },
      "gridPos": { "h": 4, "w": 6, "x": 6, "y": 0 },
      "id": 2,
      "options": {
        "colorMode": "background",
        "graphMode": "area",
        "justifyMode": "auto",
        "orientation": "auto",
        "reduceOptions": { "calcs": ["lastNotNull"], "fields": "", "values": false },
        "textMode": "auto"
      },
      "title": "Active Drivers",
      "type": "stat",
      "targets": [
        {
          "expr": "sum(lmg_drivers_active_total)",
          "legendFormat": "Active Drivers",
          "refId": "A"
        }
      ]
    },
    {
      "datasource": { "type": "prometheus", "uid": "prometheus" },
      "fieldConfig": {
        "defaults": {
          "color": { "mode": "thresholds" },
          "thresholds": {
            "mode": "absolute",
            "steps": [
              { "color": "green", "value": null },
              { "color": "yellow", "value": 50000 },
              { "color": "orange", "value": 100000 }
            ]
          },
          "unit": "currencyZAR"
        }
      },
      "gridPos": { "h": 4, "w": 6, "x": 12, "y": 0 },
      "id": 3,
      "options": {
        "colorMode": "background",
        "graphMode": "area",
        "justifyMode": "auto",
        "orientation": "auto",
        "reduceOptions": { "calcs": ["lastNotNull"], "fields": "", "values": false },
        "textMode": "auto"
      },
      "title": "Revenue Today (ZAR)",
      "type": "stat",
      "targets": [
        {
          "expr": "sum(increase(lmg_payments_revenue_zar_total[24h]))",
          "legendFormat": "Revenue",
          "refId": "A"
        }
      ]
    },
    {
      "datasource": { "type": "prometheus", "uid": "prometheus" },
      "fieldConfig": {
        "defaults": {
          "color": { "mode": "thresholds" },
          "thresholds": {
            "mode": "absolute",
            "steps": [
              { "color": "green", "value": null },
              { "color": "yellow", "value": 1 },
              { "color": "red", "value": 5 }
            ]
          },
          "unit": "percent"
        }
      },
      "gridPos": { "h": 4, "w": 6, "x": 18, "y": 0 },
      "id": 4,
      "options": {
        "colorMode": "background",
        "graphMode": "area",
        "justifyMode": "auto",
        "orientation": "auto",
        "reduceOptions": { "calcs": ["lastNotNull"], "fields": "", "values": false },
        "textMode": "auto"
      },
      "title": "Error Rate (5m)",
      "type": "stat",
      "targets": [
        {
          "expr": "100 * sum(rate(lmg_http_requests_total{status=~\"5..\"}[5m])) / sum(rate(lmg_http_requests_total[5m]))",
          "legendFormat": "Error Rate",
          "refId": "A"
        }
      ]
    },
    {
      "datasource": { "type": "prometheus", "uid": "prometheus" },
      "fieldConfig": {
        "defaults": {
          "color": { "mode": "palette-classic" },
          "custom": {
            "axisCenteredZero": false,
            "axisLabel": "Requests/sec",
            "drawStyle": "line",
            "fillOpacity": 20,
            "lineWidth": 2,
            "pointSize": 5,
            "showPoints": "never",
            "stacking": { "group": "A", "mode": "none" }
          },
          "unit": "reqps"
        }
      },
      "gridPos": { "h": 8, "w": 12, "x": 0, "y": 4 },
      "id": 5,
      "title": "Request Rate by Service",
      "type": "timeseries",
      "targets": [
        {
          "expr": "sum(rate(lmg_http_requests_total[5m])) by (service)",
          "legendFormat": "{{service}}",
          "refId": "A"
        }
      ]
    },
    {
      "datasource": { "type": "prometheus", "uid": "prometheus" },
      "fieldConfig": {
        "defaults": {
          "color": { "mode": "palette-classic" },
          "custom": {
            "axisCenteredZero": false,
            "axisLabel": "Duration (ms)",
            "drawStyle": "line",
            "fillOpacity": 10,
            "lineWidth": 2,
            "showPoints": "never"
          },
          "unit": "ms"
        }
      },
      "gridPos": { "h": 8, "w": 12, "x": 12, "y": 4 },
      "id": 6,
      "title": "P99 Latency by Service",
      "type": "timeseries",
      "targets": [
        {
          "expr": "histogram_quantile(0.99, sum(rate(lmg_http_request_duration_seconds_bucket[5m])) by (le, service)) * 1000",
          "legendFormat": "{{service}} p99",
          "refId": "A"
        }
      ]
    },
    {
      "datasource": { "type": "prometheus", "uid": "prometheus" },
      "fieldConfig": {
        "defaults": {
          "color": { "mode": "palette-classic" },
          "custom": {
            "drawStyle": "bars",
            "fillOpacity": 80,
            "stacking": { "group": "A", "mode": "normal" }
          },
          "unit": "short"
        }
      },
      "gridPos": { "h": 8, "w": 12, "x": 0, "y": 12 },
      "id": 7,
      "title": "Orders by Status (1h)",
      "type": "timeseries",
      "targets": [
        {
          "expr": "sum(increase(lmg_orders_total[1h])) by (status)",
          "legendFormat": "{{status}}",
          "refId": "A"
        }
      ]
    },
    {
      "datasource": { "type": "prometheus", "uid": "prometheus" },
      "fieldConfig": {
        "defaults": {
          "color": { "mode": "palette-classic" },
          "custom": {
            "drawStyle": "line",
            "fillOpacity": 15,
            "lineWidth": 2,
            "showPoints": "never"
          },
          "unit": "short"
        }
      },
      "gridPos": { "h": 8, "w": 12, "x": 12, "y": 12 },
      "id": 8,
      "title": "Kafka Consumer Lag by Topic",
      "type": "timeseries",
      "targets": [
        {
          "expr": "sum(kafka_consumergroup_lag) by (topic)",
          "legendFormat": "{{topic}}",
          "refId": "A"
        }
      ]
    },
    {
      "datasource": { "type": "prometheus", "uid": "prometheus" },
      "fieldConfig": {
        "defaults": {
          "color": { "mode": "palette-classic" },
          "unit": "short"
        }
      },
      "gridPos": { "h": 6, "w": 8, "x": 0, "y": 20 },
      "id": 9,
      "title": "Dispatch Match Rate",
      "type": "gauge",
      "options": {
        "minVizHeight": 75,
        "minVizWidth": 75,
        "orientation": "auto",
        "reduceOptions": { "calcs": ["lastNotNull"], "fields": "", "values": false },
        "showThresholdLabels": false,
        "showThresholdMarkers": true
      },
      "targets": [
        {
          "expr": "100 * sum(rate(lmg_dispatch_matched_total[1h])) / sum(rate(lmg_dispatch_attempts_total[1h]))",
          "legendFormat": "Match Rate %",
          "refId": "A"
        }
      ]
    },
    {
      "datasource": { "type": "prometheus", "uid": "prometheus" },
      "fieldConfig": {
        "defaults": {
          "color": { "mode": "thresholds" },
          "thresholds": {
            "mode": "absolute",
            "steps": [
              { "color": "green", "value": null },
              { "color": "yellow", "value": 300 },
              { "color": "red", "value": 600 }
            ]
          },
          "unit": "s"
        }
      },
      "gridPos": { "h": 6, "w": 8, "x": 8, "y": 20 },
      "id": 10,
      "title": "Avg Delivery Time",
      "type": "stat",
      "targets": [
        {
          "expr": "avg(lmg_delivery_duration_seconds)",
          "legendFormat": "Avg Delivery",
          "refId": "A"
        }
      ]
    },
    {
      "datasource": { "type": "prometheus", "uid": "prometheus" },
      "fieldConfig": {
        "defaults": {
          "color": { "mode": "palette-classic" },
          "unit": "short"
        }
      },
      "gridPos": { "h": 6, "w": 8, "x": 16, "y": 20 },
      "id": 11,
      "title": "Payment Gateway Success Rate",
      "type": "gauge",
      "targets": [
        {
          "expr": "100 * sum(rate(lmg_payment_success_total[1h])) / sum(rate(lmg_payment_attempts_total[1h]))",
          "legendFormat": "Success Rate %",
          "refId": "A"
        }
      ]
    }
  ],
  "refresh": "30s",
  "schemaVersion": 39,
  "tags": ["lastmile-gig", "platform", "overview"],
  "templating": {
    "list": [
      {
        "current": { "selected": false, "text": "All", "value": "$__all" },
        "datasource": { "type": "prometheus", "uid": "prometheus" },
        "definition": "label_values(lmg_http_requests_total, namespace)",
        "hide": 0,
        "includeAll": true,
        "multi": true,
        "name": "namespace",
        "query": { "query": "label_values(lmg_http_requests_total, namespace)", "refId": "A" },
        "refresh": 2,
        "type": "query"
      }
    ]
  },
  "time": { "from": "now-1h", "to": "now" },
  "title": "Lastmile Gig - Platform Overview",
  "uid": "lmg-platform-overview",
  "version": 1
}
